oc_cdtapi/API.py
oc_cdtapi/Dbsm2API.py
oc_cdtapi/DevPIAPI.py
oc_cdtapi/DmsAPI.py
oc_cdtapi/DmsGetverAPI.py
oc_cdtapi/ForemanAPI.py
oc_cdtapi/JenkinsAPI.py
oc_cdtapi/NexusAPI.py
oc_cdtapi/PgAPI.py
oc_cdtapi/PgQAPI.py
oc_cdtapi/RundeckAPI.py
oc_cdtapi/TestServer.py
oc_cdtapi/VaultAPI.py
oc_cdtapi/__init__.py
oc_cdtapi-3.31.2.data/scripts/nexus.py
oc_cdtapi-3.31.2.dist-info/licenses/LICENSE
oc_cdtapi-3.31.2.dist-info/METADATA
oc_cdtapi-3.31.2.dist-info/WHEEL
oc_cdtapi-3.31.2.dist-info/top_level.txt
oc_cdtapi-3.31.2.dist-info/RECORD
