Metadata-Version: 2.4
Name: oc-cdtapi
Version: 3.31.2
Summary: Custom Development python API libraries
License: Apache2.0
Requires-Python: >=3.6
License-File: LICENSE
Requires-Dist: requests
Requires-Dist: packaging
Requires-Dist: psycopg2-binary
Requires-Dist: hvac
Dynamic: description
Dynamic: description-content-type
Dynamic: license
Dynamic: license-file
Dynamic: requires-dist
Dynamic: requires-python
Dynamic: summary
